LICENSE
MANIFEST.in
README.md
setup.py
a10_openstack_lbaas/__init__.py
a10_openstack_lbaas/driver_v1.py
a10_openstack_lbaas.egg-info/PKG-INFO
a10_openstack_lbaas.egg-info/SOURCES.txt
a10_openstack_lbaas.egg-info/dependency_links.txt
a10_openstack_lbaas.egg-info/pbr.json
a10_openstack_lbaas.egg-info/requires.txt
a10_openstack_lbaas.egg-info/top_level.txt
tests/__init__.py
tests/units/__init__.py
tests/units/test_driver_v1.py