Metadata-Version: 1.1
Name: a10-openstack-lbaas
Version: 1.0.3
Summary: A10 Networks Openstack LBaaS Driver
Home-page: https://github.com/a10networks/a10-openstack-lbaas
Author: A10 Networks
Author-email: dougw@a10networks.com
License: Apache
Keywords: a10 axapi acos adc slb load balancer openstack neutron lbaas
Platform: UNKNOWN
Classifier: License :: OSI Approved :: Apache Software License
Classifier: Operating System :: POSIX
Classifier: Programming Language :: Python
Classifier: Programming Language :: Python :: 2.6
Classifier: Programming Language :: Python :: 2.7
Classifier: Topic :: Internet
